{
  "model": [
    {
      "candidate_name": "Sanders",
      "state": "Mississippi",
      "forecastdate": "2016-03-08",
      "poll_avg": "13.627384",
      "pollonly_winprob": 0,
      "pollonly_hi": "27.420958",
      "pollonly_lo": "3.0916305",
      "pollonly_forecast": "16.665958",
      "kitchen_winprob": 0,
      "kitchen_hi": "22.366808",
      "kitchen_lo": "9.5414028",
      "kitchen_forecast": "14.463616"
    },
    {
      "candidate_name": "Clinton",
      "state": "Mississippi",
      "forecastdate": "2016-03-08",
      "poll_avg": "64.17878",
      "pollonly_winprob": 100,
      "pollonly_hi": "87.402786",
      "pollonly_lo": "76.334869",
      "pollonly_forecast": "77.043991",
      "kitchen_winprob": 100,
      "kitchen_hi": "89.649536",
      "kitchen_lo": "78.724762",
      "kitchen_forecast": "79.24633"
    },
    {
      "candidate_name": "Sanders",
      "state": "Mississippi",
      "forecastdate": "2016-03-07",
      "poll_avg": "13.621635",
      "pollonly_winprob": 0,
      "pollonly_hi": "27.232351",
      "pollonly_lo": "3.0862451",
      "pollonly_forecast": "16.653921",
      "kitchen_winprob": 0,
      "kitchen_hi": "22.223225",
      "kitchen_lo": "9.8104877",
      "kitchen_forecast": "14.520527"
    },
    {
      "candidate_name": "Clinton",
      "state": "Mississippi",
      "forecastdate": "2016-03-07",
      "poll_avg": "64.19355",
      "pollonly_winprob": 100,
      "pollonly_hi": "87.262909",
      "pollonly_lo": "76.573944",
      "pollonly_forecast": "77.058952",
      "kitchen_winprob": 100,
      "kitchen_hi": "89.460464",
      "kitchen_lo": "78.794472",
      "kitchen_forecast": "79.192345"
    },
    {
      "candidate_name": "Sanders",
      "state": "Mississippi",
      "forecastdate": "2016-03-06",
      "poll_avg": "13.595333",
      "pollonly_winprob": 0,
      "pollonly_hi": "26.969784",
      "pollonly_lo": "3.140554",
      "pollonly_forecast": "16.637245",
      "kitchen_winprob": 0,
      "kitchen_hi": "22.114901",
      "kitchen_lo": "10.02355",
      "kitchen_forecast": "14.609288"
    },
    {
      "candidate_name": "Clinton",
      "state": "Mississippi",
      "forecastdate": "2016-03-06",
      "poll_avg": "64.196342",
      "pollonly_winprob": 100,
      "pollonly_hi": "87.100388",
      "pollonly_lo": "76.779861",
      "pollonly_forecast": "77.067986",
      "kitchen_winprob": 100,
      "kitchen_hi": "89.260254",
      "kitchen_lo": "78.875237",
      "kitchen_forecast": "79.095947"
    },
    {
      "candidate_name": "Sanders",
      "state": "Mississippi",
      "forecastdate": "2016-03-05",
      "poll_avg": "13.630173",
      "pollonly_winprob": 0,
      "pollonly_hi": "26.790096",
      "pollonly_lo": "3.1712136",
      "pollonly_forecast": "16.668385",
      "kitchen_winprob": 0,
      "kitchen_hi": "22.014915",
      "kitchen_lo": "10.134024",
      "kitchen_forecast": "14.616977"
    },
    {
      "candidate_name": "Clinton",
      "state": "Mississippi",
      "forecastdate": "2016-03-05",
      "poll_avg": "64.200287",
      "pollonly_winprob": 100,
      "pollonly_hi": "86.919144",
      "pollonly_lo": "76.968208",
      "pollonly_forecast": "77.049438",
      "kitchen_winprob": 100,
      "kitchen_hi": "89.129181",
      "kitchen_lo": "78.985764",
      "kitchen_forecast": "79.100853"
    },
    {
      "candidate_name": "Sanders",
      "state": "Mississippi",
      "forecastdate": "2016-03-04",
      "poll_avg": "13.62704",
      "pollonly_winprob": 0,
      "pollonly_hi": "26.578876",
      "pollonly_lo": "3.070152",
      "pollonly_forecast": "16.664808",
      "kitchen_winprob": 0,
      "kitchen_hi": "21.817913",
      "kitchen_lo": "10.072256",
      "kitchen_forecast": "14.507856"
    },
    {
      "candidate_name": "Clinton",
      "state": "Mississippi",
      "forecastdate": "2016-03-04",
      "poll_avg": "64.199532",
      "pollonly_winprob": 100,
      "pollonly_hi": "86.766815",
      "pollonly_lo": "77.193016",
      "pollonly_forecast": "77.051758",
      "kitchen_winprob": 100,
      "kitchen_hi": "89.139809",
      "kitchen_lo": "79.251617",
      "kitchen_forecast": "79.208702"
    },
    {
      "candidate_name": "Sanders",
      "state": "Mississippi",
      "forecastdate": "2016-03-03",
      "poll_avg": "13.627085",
      "pollonly_winprob": 0,
      "pollonly_hi": "26.344505",
      "pollonly_lo": "3.1909711",
      "pollonly_forecast": "16.664782",
      "kitchen_winprob": 0,
      "kitchen_hi": "21.640764",
      "kitchen_lo": "10.173136",
      "kitchen_forecast": "14.499225"
    },
    {
      "candidate_name": "Clinton",
      "state": "Mississippi",
      "forecastdate": "2016-03-03",
      "poll_avg": "64.199791",
      "pollonly_winprob": 100,
      "pollonly_hi": "86.58728",
      "pollonly_lo": "77.381027",
      "pollonly_forecast": "77.05188",
      "kitchen_winprob": 100,
      "kitchen_hi": "89.043877",
      "kitchen_lo": "79.420486",
      "kitchen_forecast": "79.217438"
    },
    {
      "candidate_name": "Sanders",
      "state": "Mississippi",
      "forecastdate": "2016-03-02",
      "poll_avg": "13.633023",
      "pollonly_winprob": 0,
      "pollonly_hi": "26.258682",
      "pollonly_lo": "3.1835804",
      "pollonly_forecast": "16.68638",
      "kitchen_winprob": 0,
      "kitchen_hi": "21.566021",
      "kitchen_lo": "10.35804",
      "kitchen_forecast": "14.539576"
    },
    {
      "candidate_name": "Clinton",
      "state": "Mississippi",
      "forecastdate": "2016-03-02",
      "poll_avg": "64.195328",
      "pollonly_winprob": 100,
      "pollonly_hi": "86.408371",
      "pollonly_lo": "77.575233",
      "pollonly_forecast": "77.030762",
      "kitchen_winprob": 100,
      "kitchen_hi": "88.873978",
      "kitchen_lo": "79.501282",
      "kitchen_forecast": "79.177559"
    },
    {
      "candidate_name": "Sanders",
      "state": "Mississippi",
      "forecastdate": "2016-03-01",
      "poll_avg": "26.624243"
    },
    {
      "candidate_name": "Clinton",
      "state": "Mississippi",
      "forecastdate": "2016-03-01",
      "poll_avg": "59.843918"
    },
    {
      "candidate_name": "Sanders",
      "state": "Mississippi",
      "forecastdate": "2016-02-29",
      "poll_avg": "26.687662"
    },
    {
      "candidate_name": "Clinton",
      "state": "Mississippi",
      "forecastdate": "2016-02-29",
      "poll_avg": "59.854832"
    },
    {
      "candidate_name": "Sanders",
      "state": "Mississippi",
      "forecastdate": "2016-02-28",
      "poll_avg": "26.870842"
    },
    {
      "candidate_name": "Clinton",
      "state": "Mississippi",
      "forecastdate": "2016-02-28",
      "poll_avg": "59.905907"
    },
    {
      "candidate_name": "Sanders",
      "state": "Mississippi",
      "forecastdate": "2016-02-27",
      "poll_avg": "26.939415"
    },
    {
      "candidate_name": "Clinton",
      "state": "Mississippi",
      "forecastdate": "2016-02-27",
      "poll_avg": "59.893299"
    },
    {
      "candidate_name": "Sanders",
      "state": "Mississippi",
      "forecastdate": "2016-02-26",
      "poll_avg": "26.939415"
    },
    {
      "candidate_name": "Clinton",
      "state": "Mississippi",
      "forecastdate": "2016-02-26",
      "poll_avg": "59.893299"
    },
    {
      "candidate_name": "Sanders",
      "state": "Mississippi",
      "forecastdate": "2016-02-25",
      "poll_avg": "26.92371"
    },
    {
      "candidate_name": "Clinton",
      "state": "Mississippi",
      "forecastdate": "2016-02-25",
      "poll_avg": "59.904087"
    },
    {
      "candidate_name": "Sanders",
      "state": "Mississippi",
      "forecastdate": "2016-02-24",
      "poll_avg": "27.018593"
    },
    {
      "candidate_name": "Clinton",
      "state": "Mississippi",
      "forecastdate": "2016-02-24",
      "poll_avg": "59.84557"
    },
    {
      "candidate_name": "Sanders",
      "state": "Mississippi",
      "forecastdate": "2016-02-23",
      "poll_avg": "27.000877"
    },
    {
      "candidate_name": "Clinton",
      "state": "Mississippi",
      "forecastdate": "2016-02-23",
      "poll_avg": "59.860409"
    },
    {
      "candidate_name": "Sanders",
      "state": "Mississippi",
      "forecastdate": "2016-02-22",
      "poll_avg": "26.976051"
    },
    {
      "candidate_name": "Clinton",
      "state": "Mississippi",
      "forecastdate": "2016-02-22",
      "poll_avg": "59.880978"
    },
    {
      "candidate_name": "Sanders",
      "state": "Mississippi",
      "forecastdate": "2016-02-21",
      "poll_avg": "27.1201"
    },
    {
      "candidate_name": "Clinton",
      "state": "Mississippi",
      "forecastdate": "2016-02-21",
      "poll_avg": "59.936687"
    },
    {
      "candidate_name": "Sanders",
      "state": "Mississippi",
      "forecastdate": "2016-02-20",
      "poll_avg": "27.1201"
    },
    {
      "candidate_name": "Clinton",
      "state": "Mississippi",
      "forecastdate": "2016-02-20",
      "poll_avg": "59.936687"
    },
    {
      "candidate_name": "Sanders",
      "state": "Mississippi",
      "forecastdate": "2016-02-19",
      "poll_avg": "27.10997"
    },
    {
      "candidate_name": "Clinton",
      "state": "Mississippi",
      "forecastdate": "2016-02-19",
      "poll_avg": "59.928307"
    },
    {
      "candidate_name": "Sanders",
      "state": "Mississippi",
      "forecastdate": "2016-02-18",
      "poll_avg": "27.340475"
    },
    {
      "candidate_name": "Clinton",
      "state": "Mississippi",
      "forecastdate": "2016-02-18",
      "poll_avg": "59.841827"
    },
    {
      "candidate_name": "Sanders",
      "state": "Mississippi",
      "forecastdate": "2016-02-17",
      "poll_avg": "27.590639"
    },
    {
      "candidate_name": "Clinton",
      "state": "Mississippi",
      "forecastdate": "2016-02-17",
      "poll_avg": "59.901012"
    }
  ],
  "polls": [
    {
      "id": "50080",
      "population": "lv",
      "pollId": "36525",
      "cycle": "2016",
      "sampleSize": "471",
      "state": "MS",
      "officeType": "U.S. President",
      "pollsterId": "270",
      "pollster": "Magellan Strategies",
      "startDate": "2016-02-29",
      "endDate": "2016-02-29",
      "methodology": "Live Phone",
      "tracking": null,
      "url": "http://www.yallpolitics.com/images/MS-PRESPRIM-TOPLINES.pdf",
      "stage": "primary",
      "party": "DEM",
      "created_at": 1456944720,
      "votingAnswers": [
        {
          "choice": "Clinton",
          "pct": "65.0"
        },
        {
          "choice": "Sanders",
          "pct": "11.0"
        }
      ],
      "weight": ".2890225052833557"
    },
    {
      "id": "49367",
      "population": "lv",
      "pollId": "36361",
      "cycle": "2016",
      "sampleSize": "514",
      "state": "MS",
      "officeType": "U.S. President",
      "pollsterId": "383",
      "pollster": "Public Policy Polling",
      "startDate": "2016-02-14",
      "endDate": "2016-02-16",
      "methodology": "Automated Phone",
      "tracking": null,
      "url": "http://www.publicpolicypolling.com/pdf/2015/March2016PrimariesPollingProject.pdf",
      "stage": "primary",
      "party": "DEM",
      "created_at": 1455708960,
      "votingAnswers": [
        {
          "choice": "Clinton",
          "pct": "60.0"
        },
        {
          "choice": "Sanders",
          "pct": "26.0"
        }
      ],
      "weight": ".0319182239472866"
    }
  ],
  "distributions": [
    {
      "candidate": "Clinton",
      "probs": {
        "pollonly": [
          "5.6577628e-11",
          "8.1672430e-10",
          "2.9214560e-09",
          "6.2254069e-09",
          "1.0287362e-08",
          "1.4657826e-08",
          "1.8971296e-08",
          "2.2963784e-08",
          "2.6463697e-08",
          "2.9374414e-08",
          "3.1656672e-08",
          "3.3312588e-08",
          "3.4372849e-08",
          "3.4886565e-08",
          "3.4913441e-08",
          "3.4518212e-08",
          "3.3766664e-08",
          "3.2722323e-08",
          "3.1445037e-08",
          "2.9989785e-08",
          "2.8405587e-08",
          "2.6735972e-08",
          "2.5018325e-08",
          "2.3284592e-08",
          "2.1561551e-08",
          "1.9870932e-08",
          "1.8230391e-08",
          "1.6653368e-08",
          "1.5150253e-08",
          "1.3728294e-08",
          "1.2392113e-08",
          "1.1144429e-08",
          "9.9860431e-09",
          "8.9162153e-09",
          "7.9332079e-09",
          "7.0342527e-09",
          "6.2158207e-09",
          "5.4739937e-09",
          "4.8044213e-09",
          "4.2026156e-09",
          "3.6640955e-09",
          "3.1849237e-09",
          "2.7625706e-09",
          "2.3984601e-09",
          "2.1045528e-09",
          "1.9198192e-09",
          "1.9512132e-09",
          "2.4722970e-09",
          "4.1539385e-09",
          "8.5895548e-09",
          "1.9458707e-08",
          "4.5034881e-08",
          "1.0344692e-07",
          "2.3342434e-07",
          "5.1563870e-07",
          "1.1139932e-06",
          "2.3532245e-06",
          "4.8607426e-06",
          "9.8183300e-06",
          ".000019395513",
          ".000037470956",
          ".000070796435",
          ".00013080027",
          ".00023627446",
          ".00041719154",
          ".00071983755",
          ".001213209",
          ".0019963547",
          ".0032054379",
          ".005018637",
          ".007655635",
          ".011367522",
          ".016411677",
          ".023008889",
          ".031278767",
          ".041159645",
          ".052323952",
          ".06411168",
          ".075513028",
          ".085229449",
          ".091845386",
          ".094090961",
          ".091167256",
          ".083037965",
          ".070578091",
          ".055479188",
          ".039893318",
          ".025885249",
          ".014897568",
          ".0074389442",
          ".0031313018",
          ".0010690978",
          ".00028081538",
          ".000052640597",
          "6.3022171e-06",
          "4.0521002e-07",
          "1.0451073e-08",
          "6.2211188e-11",
          "2.3869776e-14",
          "0"
        ],
        "kitchen": [
          "3.2442528e-11",
          "2.2645004e-10",
          "5.3979327e-10",
          "8.9484181e-10",
          "1.2470778e-09",
          "1.5723864e-09",
          "1.8585780e-09",
          "2.1005135e-09",
          "2.2972602e-09",
          "2.4503466e-09",
          "2.5627176e-09",
          "2.6380453e-09",
          "2.6803155e-09",
          "2.6935620e-09",
          "2.6816942e-09",
          "2.6484070e-09",
          "2.5971387e-09",
          "2.5310063e-09",
          "2.4528346e-09",
          "2.3651598e-09",
          "2.2702049e-09",
          "2.1699507e-09",
          "2.0661033e-09",
          "1.9601483e-09",
          "1.8533692e-09",
          "1.7468397e-09",
          "1.6414865e-09",
          "1.5380531e-09",
          "1.4371790e-09",
          "1.3393676e-09",
          "1.2450053e-09",
          "1.1544090e-09",
          "1.0678017e-09",
          "9.8532771e-10",
          "9.0708940e-10",
          "8.3312729e-10",
          "7.6343315e-10",
          "6.9798217e-10",
          "6.3672617e-10",
          "5.7964594e-10",
          "5.2683569e-10",
          "4.7876253e-10",
          "4.3686738e-10",
          "4.0510764e-10",
          "3.9372156e-10",
          "4.2814105e-10",
          "5.6970212e-10",
          "9.6257569e-10",
          "1.9375928e-09",
          "4.2367421e-09",
          "9.4878407e-09",
          "2.1185562e-08",
          "4.6674959e-08",
          "1.0107506e-07",
          "2.1486484e-07",
          "4.4825165e-07",
          "9.1775098e-07",
          "1.8443001e-06",
          "3.6383524e-06",
          "7.0469382e-06",
          ".000013401263",
          ".000025024434",
          ".000045882702",
          ".000082598461",
          ".00014597573",
          ".00025322111",
          ".00043103658",
          ".00071976922",
          ".0011785944",
          ".0018915579",
          ".0029737873",
          ".0045766016",
          ".0068891165",
          ".01013379",
          ".014550956",
          ".02036898",
          ".027756233",
          ".036754739",
          ".047201056",
          ".058645833",
          ".070301481",
          ".081039578",
          ".089480571",
          ".094192207",
          ".093991697",
          ".088294715",
          ".077419393",
          ".062690899",
          ".046253122",
          ".030557556",
          ".017670114",
          ".0086734928",
          ".0034643142",
          ".0010598828",
          ".00022700526",
          ".000029553541",
          "1.8431153e-06",
          "3.5188176e-08",
          "7.4047650e-11",
          "0"
        ]
      }
    },
    {
      "candidate": "Sanders",
      "probs": {
        "pollonly": [
          ".01010765",
          ".027444176",
          ".032094266",
          ".030520994",
          ".026750859",
          ".022528306",
          ".018559527",
          ".015093363",
          ".012185031",
          ".0098285675",
          ".0080434419",
          ".0069455868",
          ".0067947353",
          ".0079856813",
          ".010956797",
          ".016025322",
          ".02320433",
          ".032079499",
          ".041808922",
          ".051259644",
          ".059238866",
          ".064746708",
          ".067169778",
          ".066370413",
          ".062659867",
          ".056681171",
          ".049250163",
          ".041194998",
          ".033234637",
          ".025904903",
          ".019537069",
          ".014275584",
          ".010117723",
          ".0069624274",
          ".0046560736",
          ".003028356",
          ".00191706",
          ".0011819839",
          ".00071029051",
          ".0004163346",
          ".00023824809",
          ".00013327136",
          ".000073001596",
          ".000039261584",
          ".000020817053",
          ".000010949273",
          "5.7655225e-06",
          "3.0778194e-06",
          "1.6913177e-06",
          "9.7121506e-07",
          "5.8867590e-07",
          "3.7702785e-07",
          "2.5318579e-07",
          "1.7604820e-07",
          "1.2515078e-07",
          "9.0039940e-08",
          "6.5095477e-08",
          "4.7076504e-08",
          "3.3961335e-08",
          "2.4398336e-08",
          "1.7436667e-08",
          "1.2387718e-08",
          "8.7438536e-09",
          "6.1290333e-09",
          "4.2644288e-09",
          "2.9438105e-09",
          "2.0151993e-09",
          "1.3673016e-09",
          "9.1895985e-10",
          "6.1142480e-10",
          "4.0244436e-10",
          "2.6185432e-10",
          "1.6828142e-10",
          "1.0671933e-10",
          "6.6716466e-11",
          "4.1068492e-11",
          "2.4860693e-11",
          "1.4778144e-11",
          "8.6123027e-12",
          "4.9112754e-12",
          "2.7347991e-12",
          "1.4833367e-12",
          "7.8142516e-13",
          "3.9851279e-13",
          "1.9595008e-13",
          "9.2442011e-14",
          "4.1619150e-14",
          "1.7759664e-14",
          "7.1254571e-15",
          "2.6450563e-15",
          "8.9068214e-16",
          "2.6990369e-16",
          "8.0971109e-17",
          "2.6990369e-17",
          "0",
          "0",
          "0",
          "0",
          "0",
          "0"
        ],
        "kitchen": [
          ".0023007528",
          ".0031916166",
          ".002724167",
          ".0021881599",
          ".0018669461",
          ".0021421593",
          ".0037077579",
          ".0074351337",
          ".013997769",
          ".023492118",
          ".035275172",
          ".048086364",
          ".060371164",
          ".070657074",
          ".077851884",
          ".081397913",
          ".081279308",
          ".077919237",
          ".072024778",
          ".064424194",
          ".055929769",
          ".047245461",
          ".038915552",
          ".031312574",
          ".024650153",
          ".01901068",
          ".014379662",
          ".010678044",
          ".007791027",
          ".0055894605",
          ".0039453176",
          ".002741352",
          ".0018759196",
          ".0012647186",
          ".00084033102",
          ".00055043353",
          ".00035551551",
          ".00022646907",
          ".00014231203",
          ".000088236135",
          ".000053990923",
          ".00003261345",
          ".000019455852",
          ".000011469226",
          "6.6870648e-06",
          "3.8612657e-06",
          "2.2124568e-06",
          "1.2616728e-06",
          "7.1906953e-07",
          "4.1196401e-07",
          "2.3903692e-07",
          "1.4170659e-07",
          "8.6589395e-08",
          "5.4915052e-08",
          "3.6254789e-08",
          "2.4872227e-08",
          "1.7628944e-08",
          "1.2808816e-08",
          "9.4654062e-09",
          "7.0662844e-09",
          "5.3015521e-09",
          "3.9825379e-09",
          "2.9876710e-09",
          "2.2343427e-09",
          "1.6636973e-09",
          "1.2323061e-09",
          "9.0734320e-10",
          "6.6371764e-10",
          "4.8207244e-10",
          "3.4747419e-10",
          "2.4841004e-10",
          "1.7603265e-10",
          "1.2356717e-10",
          "8.5860756e-11",
          "5.9009284e-11",
          "4.0076741e-11",
          "2.6870842e-11",
          "1.7766439e-11",
          "1.1569157e-11",
          "7.4088678e-12",
          "4.6584563e-12",
          "2.8703945e-12",
          "1.7293772e-12",
          "1.0161566e-12",
          "5.8052966e-13",
          "3.2127938e-13",
          "1.7148662e-13",
          "8.7802439e-14",
          "4.2834392e-14",
          "1.9743962e-14",
          "8.5019501e-15",
          "3.3730120e-15",
          "1.2087306e-15",
          "3.7977011e-16",
          "1.0208874e-16",
          "2.0417747e-17",
          "4.0835496e-18",
          "0",
          "0",
          "0"
        ]
      }
    }
  ]
}